[
    {
        "tag_id": 1,
        "genre": "Action"
    },
    {
        "tag_id": 2,
        "genre": "Adventure"
    },
    {
        "tag_id": 3,
        "genre": "Comedy"
    },
    {
        "tag_id": 4,
        "genre": "Drama"
    },
    {
        "tag_id": 5,
        "genre": "Fantasy"
    },
    {
        "tag_id": 6,
        "genre": "Horror"
    },
    {
        "tag_id": 7,
        "genre": "Mystery"
    },
    {
        "tag_id": 8,
        "genre": "Romance"
    },
    {
        "tag_id": 9,
        "genre": "Sci-Fi"
    },
    {
        "tag_id": 10,
        "genre": "Thriller"
    },
    {
        "tag_id": 11,
        "genre": "Crime"
    },
    {
        "tag_id": 12,
        "genre": "Animation"
    },
    {
        "tag_id": 13,
        "genre": "Biography"
    },
    {
        "tag_id": 14,
        "genre": "Family"
    },
    {
        "tag_id": 15,
        "genre": "History"
    },
    {
        "tag_id": 16,
        "genre": "Musical"
    },
    {
        "tag_id": 17,
        "genre": "Sport"
    },
    {
        "tag_id": 18,
        "genre": "War"
    },
    {
        "tag_id": 19,
        "genre": "Western"
    },
    {
        "tag_id": 20,
        "genre": "Documentary"
    }
]